tlcode/__init__.py
tlcode/exp.py
code_podu-0.1.dist-info/METADATA
code_podu-0.1.dist-info/WHEEL
code_podu-0.1.dist-info/top_level.txt
code_podu-0.1.dist-info/RECORD
