Metadata-Version: 2.1
Name: code-podu
Version: 0.1
Summary: Collection of ML experiments as reusable package
Author: kandupudi
Requires-Dist: tensorflow
Requires-Dist: matplotlib
Requires-Dist: kagglehub
Requires-Dist: opendatasets
Requires-Dist: scikit-learn
Requires-Dist: transformers
Requires-Dist: datasets
Requires-Dist: torch
Requires-Dist: seaborn
